packagefoldertwo/__init__.py
packagefoldertwo/ex.py
packagefoldertwo/simplecomponenttwo.py
simpleslidertitle-0.0.6.dist-info/LICENSE.txt
simpleslidertitle-0.0.6.dist-info/METADATA
simpleslidertitle-0.0.6.dist-info/WHEEL
simpleslidertitle-0.0.6.dist-info/top_level.txt
simpleslidertitle-0.0.6.dist-info/RECORD
