Metadata-Version: 2.1
Name: simpleslidertitle
Version: 0.0.6
Summary: Package slider title
Home-page: UNKNOWN
Author: TW
Author-email: TW@example.com
License: UNKNOWN
Platform: UNKNOWN
Classifier: Programming Language :: Python :: 3
Classifier: License :: OSI Approved :: MIT License
Classifier: Operating System :: OS Independent
Requires-Python: >=3.6
License-File: LICENSE.txt
